[{
    "ID": "001",
   "Name": "TestWell001",
    "Type": "rls",
    "Source": "101010"
},
{
    "ID": "002",
    "Name": "TestWell002",
    "Type": "esp",
    "Source": "10001001" 
},
{
    "ID": "003",
    "Name": "TestWell003",
    "Type": "rls",
    "Source": "1000001" 
},
{
    "ID": "004",
   "Name": "TestWell004",
    "Type": "rls",
    "Source": "101010"
},
{
    "ID": "005",
    "Name": "TestWell005",
    "Type": "esp",
    "Source": "10001001" 
},
{
    "ID": "006",
    "Name": "TestWell006",
    "Type": "esp",
    "Source": "1000001" 
}]